{
  "clientId": "1-e724f5a9e6f1",
  "copublisher": {},
  "noctua": {
    "disableCustomEvent": false,
    "disableTracker": true,
    "trackerUrl": "",
    "baseUrl": "https://sdk-api-v2.noctuaprojects.com/api/v1",
    "paymentBaseUrl": "https://dev.noctua.gg/noctua-gold-payment-webview",
    "eventMap": {}
  },
  "adjust": {
    "eventMap": {
      "start_download_resources": "bocpep",
      "complete_download_resources": "l0uu5l",
      "start_registration": "q3h6e9",
      "register": "7yyqf9",
      "login": "m0wvps",
      "create_role": "zb1frr",
      "tutorial_complete": "rrw5nu",
      "first_topup": "9mwubq",
      "purchase": "9mwubq"
    }
  },
  "firebase": {
    "eventMap": {
      "start_download_resources": "fire_start_download_resources_ios",
      "complete_download_resources": "fire_complete_download_resources_ios",
      "start_registration": "fire_start_registration_ios",
      "register": "fire_register_ios",
      "login": "fire_login_ios",
      "create_role": "fire_create_role_ios",
      "tutorial_complete": "fire_tutorial_complete_ios",
      "first_topup": "fire_first_topup_ios",
      "purchase": "fire_purchase_ios"
    }
  },
  "facebook": {
    "appId": "807936677546640",
    "clientToken": "5eb9cb06333460b31c60e484676110a0",
    "displayName": "SDK Test Noctua",
    "enableDebug": true,
    "eventMap": {
      "start_download_resources": "fb_start_download_resources_ios",
      "complete_download_resources": "fb_complete_download_resources_ios",
      "start_registration": "fb_start_registration_ios",
      "register": "fb_register_ios",
      "login": "fb_login_ios",
      "create_role": "fb_create_role_ios",
      "tutorial_complete": "fb_tutorial_complete_ios",
      "first_topup": "fb_first_topup_ios",
      "purchase": "fb_purchase_ios"
    }
  }
}
