{
  "clientId": "1-e724f5a9e6f1",
  "copublisher": {},
  "noctua": {
    "disableCustomEvent": false,
    "disableTracker": true,
    "trackerUrl": "",
    "baseUrl": "https://sdk-api-v2.noctuaprojects.com/api/v1",
    "paymentBaseUrl": "https://dev.noctua.gg/noctua-gold-payment-webview",
    "eventMap": {}
  },
  "adjust": {
    "eventMap": {
      "start_download_resources": "nbefop",
      "complete_download_resources": "aqpv4k",
      "start_registration": "oelnmn",
      "register": "byre54",
      "login": "uae3l3",
      "create_role": "6f2oaz",
      "tutorial_complete": "jtcg4l",
      "first_topup": "e8v6ax",
      "purchase": "wzi98m"
    }
  },
  "firebase": {
    "eventMap": {
      "start_download_resources": "fire_start_download_resources_windows",
      "complete_download_resources": "fire_complete_download_resources_windows",
      "start_registration": "fire_start_registration_windows",
      "register": "fire_register_windows",
      "login": "fire_login_windows",
      "create_role": "fire_create_role_windows",
      "tutorial_complete": "fire_tutorial_complete_windows",
      "first_topup": "fire_first_topup_windows",
      "purchase": "fire_purchase_windows"
    }
  },
  "facebook": {
    "appId": "807936677546640",
    "clientToken": "5eb9cb06333460b31c60e484676110a0",
    "displayName": "SDK Test Noctua",
    "enableDebug": true,
    "eventMap": {
      "start_download_resources": "fb_start_download_resources_windows",
      "complete_download_resources": "fb_complete_download_resources_windows",
      "start_registration": "fb_start_registration_windows",
      "register": "fb_register_windows",
      "login": "fb_login_windows",
      "create_role": "fb_create_role_windows",
      "tutorial_complete": "fb_tutorial_complete_windows",
      "first_topup": "fb_first_topup_windows",
      "purchase": "fb_purchase_windows"
    }
  }
}
